{
  "version": 1,
  "images": {
    "deviceSizes": [
      640,
      750,
      828,
      1080,
      1200,
      1920,
      2048,
      3840
    ],
    "imageSizes": [
      16,
      32,
      48,
      64,
      96,
      128,
      256,
      384
    ],
    "path": "/_next/image",
    "loader": "default",
    "loaderFile": "",
    "domains": [],
    "disableStaticImages": false,
    "minimumCacheTTL": 60,
    "formats": [
      "image/webp"
    ],
    "dangerouslyAllowSVG": false,
    "contentSecurityPolicy": "script-src 'none'; frame-src 'none'; sandbox;",
    "contentDispositionType": "attachment",
    "remotePatterns": [
      {
        "protocol": "https",
        "hostname": "^(?:^(?:avatars\\.yandex\\.net)$)$",
        "port": "",
        "pathname": "^(?:\\/get-music-content(?:\\/(?!\\.{1,2}(?:\\/|$))(?:(?:(?!(?:^|\\/)\\.{1,2}(?:\\/|$)).)*?)|$))$"
      },
      {
        "protocol": "https",
        "hostname": "^(?:^(?:avatars\\.yandex\\.ru)$)$",
        "port": "",
        "pathname": "^(?:\\/get-music-content(?:\\/(?!\\.{1,2}(?:\\/|$))(?:(?:(?!(?:^|\\/)\\.{1,2}(?:\\/|$)).)*?)|$))$"
      },
      {
        "protocol": "https",
        "hostname": "^(?:^(?:music\\.yandex\\.net)$)$",
        "port": "",
        "pathname": "^(?:\\/(?!\\.{1,2}(?:\\/|$))(?:(?:(?!(?:^|\\/)\\.{1,2}(?:\\/|$)).)*?))$"
      },
      {
        "protocol": "https",
        "hostname": "^(?:^(?:music\\.yandex\\.ru)$)$",
        "port": "",
        "pathname": "^(?:\\/(?!\\.{1,2}(?:\\/|$))(?:(?:(?!(?:^|\\/)\\.{1,2}(?:\\/|$)).)*?))$"
      },
      {
        "protocol": "https",
        "hostname": "^(?:^(?:lesyasvet\\.storage\\.yandexcloud\\.net)$)$",
        "port": "",
        "pathname": "^(?:\\/(?!\\.{1,2}(?:\\/|$))(?:(?:(?!(?:^|\\/)\\.{1,2}(?:\\/|$)).)*?))$"
      },
      {
        "protocol": "https",
        "hostname": "^(?:(?!\\.)(?=.)[^/]*?\\.storage\\.yandexcloud\\.net\\/?)$",
        "port": "",
        "pathname": "^(?:\\/(?!\\.{1,2}(?:\\/|$))(?:(?:(?!(?:^|\\/)\\.{1,2}(?:\\/|$)).)*?))$"
      }
    ],
    "unoptimized": false,
    "sizes": [
      640,
      750,
      828,
      1080,
      1200,
      1920,
      2048,
      3840,
      16,
      32,
      48,
      64,
      96,
      128,
      256,
      384
    ]
  }
}