{
  "blocks": [
    {
      "type": "text",
      "content": "Alphonse Mucha’s ",
      "style": "title"
    },
    {
      "type": "quote",
      "content": "Идейные соображения высшего порядка, а также начало повседневной работы",
      "style": "big"
    },
    {
      "type": "image",
      "title": "Особенный момент для особенного человека",
      "text": "Идейные соображения высшего порядка, а также начало повседневной работы",
      "url": "/uploads/1748387472814_Group_2.svg",
      "caption": "Особенный момент для особенного человека (24/10/2023)",
      "layout": "image-right",
      "size": "small",
      "orientation": "vertical"
    },
    {
      "type": "two-images",
      "images": [
        {
          "title": "Деятели",
          "text": "Идейные соображения высшего порядка, а также начало повседневной работы",
          "url": "/uploads/1748376783165_image.png",
          "layout": "text-top"
        },
       {
          "title": "Товарищи",
          "text": "Идейные соображения высшего порядка, а также начало повседневной работы",
          "url": "/uploads/1748376793006_image-1.png",
          "layout": "text-bottom"
       } 
      ],
      "size": "small",
      "orientation": "vertical"
    },
    {
      "type": "video-circle",
      "title": "Особенный момент для особенного человека",
      "text": "Идейные соображения высшего порядка, а также начало повседневной работы",
      "url": "/uploads/1748377183538_doc_2025-05-28_01-16-23.mp4",
      "caption": "Особенный момент для особенного человека (24/10/2023)",
      "size": "large",
      "muted": false
    },
    {
      "type": "video",
      "title": "Особенный момент для особенного человека",
      "text": "Идейные соображения высшего порядка, а также начало повседневной работы",
      "url": "/uploads/1748377208083_IMG_3693.MP4",
      "caption": "Особенный момент для особенного человека (24/10/2023)",
      "size": "large",
      "orientation": "horizontal"
    },
    {
      "type": "audio-message",
      "title": "Особенный момент для особенного человека",
      "text": "Идейные соображения высшего порядка, а также начало повседневной работы",
      "url": "/uploads/1748377230283_audio_2025-05-28_01-17-15.ogg"
    },
    {
      "type": "music",
      "title": "Любимая мелодия",
      "text": "Включи и вспомни наши лучшие моменты",

      "url": "/uploads/1748377217576_____-________-________.mp3",
      "coverUrl": "https://avatars.yandex.net/get-music-content/2411511/3060183d.a.12044614-1/m1000x1000",
      "artist": "ЛСП",
      "trackName": "Девочка-пришелец"
    }
  ],
  "metadata": {
    "description": "Разнообразный и богатый опыт дальнейшее развитие различных форм деятельности в значительной степени обуславливает создание позиций, занимаемых участниками в отношении поставленных задач. С другой стороны новая модель организационной деятельности играет важную роль в формировании системы обучения кадров 💋",
    "senderName": "Даши",
    "createdAt": "2025-05-26T22:42:34.826Z"
  }
}